cbeitss/__init__.py
cbeitss/fun1.py
cbeitss/fun2.py
cbeitss-0.2.dist-info/LICENCE
cbeitss-0.2.dist-info/METADATA
cbeitss-0.2.dist-info/WHEEL
cbeitss-0.2.dist-info/top_level.txt
cbeitss-0.2.dist-info/RECORD
