Metadata-Version: 2.1
Name: cbeitss
Version: 0.2
Summary: simple package
Home-page: UNKNOWN
Author: Nithingowda A M
Author-email: nithingowdaam.itss@gmail.com
License: MIT
Platform: UNKNOWN
Classifier: Programming Language :: Python :: 2
Classifier: Programming Language :: Python :: 2.7
Classifier: License :: OSI Approved :: MIT License
